social_user_info/__init__.py
social_user_info/constants.py
social_user_info/social_user_info.py
social_user_info/status_codes.py
social_user_info/social_medias/__init__.py
social_user_info/social_medias/abstract_social_media.py
social_user_info/social_medias/facebook.py
social_user_info/social_medias/github.py
social_user_info/social_medias/google.py
social_user_info/social_medias/microsoft.py
social_user_info-1.1.0.dist-info/LICENSE
social_user_info-1.1.0.dist-info/METADATA
social_user_info-1.1.0.dist-info/WHEEL
social_user_info-1.1.0.dist-info/top_level.txt
social_user_info-1.1.0.dist-info/RECORD
